zensols/mimicsid/resources/adm.conf
zensols/mimicsid/resources/anon.conf
zensols/mimicsid/resources/app.conf
zensols/mimicsid/resources/default.conf
zensols/mimicsid/resources/obj.conf
zensols/mimicsid/resources/ontology.csv
zensols/mimicsid/__init__.py
zensols/mimicsid/anon.py
zensols/mimicsid/app.py
zensols/mimicsid/cli.py
zensols/mimicsid/compat.py
zensols/mimicsid/dapp.py
zensols/mimicsid/domain.py
zensols/mimicsid/model.py
zensols/mimicsid/pred.py
zensols_mimicsid-1.10.1.dist-info/METADATA
zensols_mimicsid-1.10.1.dist-info/WHEEL
zensols_mimicsid-1.10.1.dist-info/entry_points.txt
zensols_mimicsid-1.10.1.dist-info/licenses/LICENSE.md
zensols_mimicsid-1.10.1.dist-info/RECORD
