Metadata-Version: 2.3
Name: zensols_mimicsid
Version: 1.10.1
Summary: This repository contains the a Python package to automatically segment and identify sections of clinical notes, such as electronic health record (EHR) medical documents.
Project-URL: Homepage, https://github.com/plandes/mimicsid
Project-URL: Documentation, https://plandes.github.io/mimicsid
Project-URL: Repository, https://github.com/plandes/mimicsid.git
Project-URL: Issues, https://github.com/plandes/mimicsid/issues
Project-URL: Changelog, https://github.com/plandes/mimicsid/blob/master/CHANGELOG.md
Author-email: Paul Landes <landes@mailc.net>
License: MIT
Keywords: annotation,clinical,deep learning,mimic,natural language processing
Requires-Python: <3.13,>=3.11
Requires-Dist: zensols-deepnlp~=1.18.0
Requires-Dist: zensols-mimic==1.9.2
